comfy_cli/__init__.py
comfy_cli/__main__.py
comfy_cli/cmdline.py
comfy_cli/config_manager.py
comfy_cli/constants.py
comfy_cli/env_checker.py
comfy_cli/logging.py
comfy_cli/meta_data.py
comfy_cli/tracking.py
comfy_cli/ui.py
comfy_cli/utils.py
comfy_cli/workspace_manager.py
comfy_cli/command/__init__.py
comfy_cli/command/install.py
comfy_cli/command/run.py
comfy_cli/command/custom_nodes/__init__.py
comfy_cli/command/custom_nodes/command.py
comfy_cli/command/models/models.py
comfy_cli-2024.5.1.dist-info/LICENSE
comfy_cli-2024.5.1.dist-info/METADATA
comfy_cli-2024.5.1.dist-info/WHEEL
comfy_cli-2024.5.1.dist-info/entry_points.txt
comfy_cli-2024.5.1.dist-info/top_level.txt
comfy_cli-2024.5.1.dist-info/RECORD
