Metadata-Version: 2.1
Name: comfy-cli
Version: 2024.5.1
Summary: A CLI tool for installing and using ComfyUI.
Maintainer-email: Yoland Yan <yoland@drip.art>, James Kwon <hongilkwon316@gmail.com>, Robin Huang <robin@drip.art>, "Dr.Lt.Data" <dr.lt.data@gmail.com>
License: GNU GENERAL PUBLIC LICENSE
Project-URL: Repository, https://github.com/drip-art/comfy-cli.git
Keywords: comfyui,stable diffusion
Classifier: Development Status :: 4 - Beta
Classifier: Intended Audience :: Developers
Classifier: License :: OSI Approved :: GNU General Public License v3 (GPLv3)
Requires-Python: >=3.8
License-File: LICENSE
Requires-Dist: typer >=0.3.0
Requires-Dist: GitPython
Requires-Dist: rich
Requires-Dist: requests
Requires-Dist: pyyaml
Requires-Dist: typing-extensions
Requires-Dist: mixpanel
Requires-Dist: questionary
Requires-Dist: psutil
